[
  {
    "ContainingType": "API_LocalizationPractice.Controllers.CategoriesController",
    "Method": "Index",
    "RelativePath": "api/Categories",
    "HttpMethod": "GET",
    "IsController": true,
    "Order": 0,
    "Parameters": [
      {
        "Name": "lang",
        "Type": "System.String",
        "IsRequired": false
      }
    ],
    "ReturnTypes": []
  },
  {
    "ContainingType": "API_LocalizationPractice.Controllers.CategoriesController",
    "Method": "Create",
    "RelativePath": "api/Categories",
    "HttpMethod": "POST",
    "IsController": true,
    "Order": 0,
    "Parameters": [
      {
        "Name": "request",
        "Type": "API_LocalizationPractice.DTO.Requests.CategoryRequestDTO",
        "IsRequired": true
      }
    ],
    "ReturnTypes": []
  },
  {
    "ContainingType": "API_LocalizationPractice.Controllers.CategoriesController",
    "Method": "Details",
    "RelativePath": "api/Categories/{ID}",
    "HttpMethod": "GET",
    "IsController": true,
    "Order": 0,
    "Parameters": [
      {
        "Name": "ID",
        "Type": "System.Int32",
        "IsRequired": true
      }
    ],
    "ReturnTypes": []
  },
  {
    "ContainingType": "API_LocalizationPractice.Controllers.CategoriesController",
    "Method": "Update",
    "RelativePath": "api/Categories/{ID}",
    "HttpMethod": "PATCH",
    "IsController": true,
    "Order": 0,
    "Parameters": [
      {
        "Name": "ID",
        "Type": "System.Int32",
        "IsRequired": true
      },
      {
        "Name": "request",
        "Type": "API_LocalizationPractice.DTO.Requests.CategoryRequestDTO",
        "IsRequired": true
      }
    ],
    "ReturnTypes": []
  },
  {
    "ContainingType": "API_LocalizationPractice.Controllers.CategoriesController",
    "Method": "Delete",
    "RelativePath": "api/Categories/{ID}",
    "HttpMethod": "DELETE",
    "IsController": true,
    "Order": 0,
    "Parameters": [
      {
        "Name": "ID",
        "Type": "System.Int32",
        "IsRequired": true
      }
    ],
    "ReturnTypes": []
  },
  {
    "ContainingType": "API_LocalizationPractice.Controllers.CategoriesController",
    "Method": "IndexAll",
    "RelativePath": "api/Categories/All",
    "HttpMethod": "GET",
    "IsController": true,
    "Order": 0,
    "Parameters": [
      {
        "Name": "lang",
        "Type": "System.String",
        "IsRequired": false
      }
    ],
    "ReturnTypes": []
  },
  {
    "ContainingType": "API_LocalizationPractice.Controllers.CategoriesController",
    "Method": "DeleteAll",
    "RelativePath": "api/Categories/DeleteAll",
    "HttpMethod": "DELETE",
    "IsController": true,
    "Order": 0,
    "Parameters": [],
    "ReturnTypes": []
  },
  {
    "ContainingType": "API_LocalizationPractice.Controllers.CategoriesController",
    "Method": "ToggleStatus",
    "RelativePath": "api/Categories/ToggleStatus/{ID}",
    "HttpMethod": "PATCH",
    "IsController": true,
    "Order": 0,
    "Parameters": [
      {
        "Name": "ID",
        "Type": "System.Int32",
        "IsRequired": true
      }
    ],
    "ReturnTypes": []
  }
]